nba_transactions_scraper/__init__.py
nba_transactions_scraper/api.py
nba_transactions_scraper/main copy.py
nba_transactions_scraper/main.py
nba_transactions_scraper-1.1.0.dist-info/LICENSE
nba_transactions_scraper-1.1.0.dist-info/METADATA
nba_transactions_scraper-1.1.0.dist-info/WHEEL
nba_transactions_scraper-1.1.0.dist-info/top_level.txt
nba_transactions_scraper-1.1.0.dist-info/RECORD
