Metadata-Version: 2.1
Name: nba-transactions-scraper
Version: 1.1.0
Summary: A package for scraping NBA trades and transactions.
Home-page: https://github.com/seleanridley/nba-transactions-scraper
Author: Dominic Ridley
Author-email: dominicsridley@gmail.com
License: UNKNOWN
Project-URL: Bug Tracker, https://github.com/seleanridley/nba-transactions-scraper/issues
Platform: UNKNOWN
Classifier: Programming Language :: Python :: 3
Classifier: License :: OSI Approved :: MIT License
Classifier: Operating System :: OS Independent
Requires-Python: >=3.6
License-File: LICENSE
Requires-Dist: beautifulsoup4
Requires-Dist: flask
Requires-Dist: flask-restful
Requires-Dist: pandas
Requires-Dist: requests
Requires-Dist: nba-api
